{
  "main": {
    "id": "4dec962a3002d619",
    "type": "split",
    "children": [
      {
        "id": "59a58bee3784a5a6",
        "type": "tabs",
        "children": [
          {
            "id": "bb98973169500b1a",
            "type": "leaf",
            "state": {
              "type": "markdown",
              "state": {
                "file": "游戏创意/完整/Mist Castle/剧本/实验记录.md",
                "mode": "source",
                "source": false,
                "backlinks": true,
                "backlinkOpts": {
                  "collapseAll": false,
                  "extraContext": false,
                  "sortOrder": "alphabetical",
                  "showSearch": false,
                  "searchQuery": "",
                  "backlinkCollapsed": false,
                  "unlinkedCollapsed": true
                }
              },
              "icon": "lucide-file",
              "title": "实验记录"
            }
          },
          {
            "id": "c35252fe7b2c993e",
            "type": "leaf",
            "state": {
              "type": "release-notes",
              "state": {
                "currentVersion": "1.8.7"
              },
              "icon": "lucide-book-up",
              "title": "Release Notes 1.8.7"
            }
          }
        ]
      }
    ],
    "direction": "vertical"
  },
  "left": {
    "id": "8fa3ec390cfaec9b",
    "type": "split",
    "children": [
      {
        "id": "d13837baec1c54fa",
        "type": "tabs",
        "children": [
          {
            "id": "ac131cef62963c98",
            "type": "leaf",
            "state": {
              "type": "file-explorer",
              "state": {
                "sortOrder": "alphabetical",
                "autoReveal": false
              },
              "icon": "lucide-folder-closed",
              "title": "文件列表"
            }
          },
          {
            "id": "48c63909c6c01f02",
            "type": "leaf",
            "state": {
              "type": "bookmarks",
              "state": {},
              "icon": "lucide-bookmark",
              "title": "书签"
            }
          },
          {
            "id": "a11e591afee998c9",
            "type": "leaf",
            "state": {
              "type": "search",
              "state": {
                "query": "",
                "matchingCase": false,
                "explainSearch": false,
                "collapseAll": false,
                "extraContext": false,
                "sortOrder": "alphabetical"
              },
              "icon": "lucide-search",
              "title": "Search"
            }
          },
          {
            "id": "c6c5d980814a5592",
            "type": "leaf",
            "state": {
              "type": "mk-path-view",
              "state": {},
              "icon": "layout-grid",
              "title": "Navigator"
            }
          }
        ],
        "currentTab": 3
      }
    ],
    "direction": "horizontal",
    "width": 344.5
  },
  "right": {
    "id": "b7c807921f6b7bb3",
    "type": "split",
    "children": [
      {
        "id": "2a2da756c5a510d0",
        "type": "tabs",
        "children": [
          {
            "id": "688cd7ac3ea74401",
            "type": "leaf",
            "state": {
              "type": "backlink",
              "state": {
                "file": "游戏创意/骰出重围.md",
                "collapseAll": false,
                "extraContext": false,
                "sortOrder": "alphabetical",
                "showSearch": false,
                "searchQuery": "",
                "backlinkCollapsed": false,
                "unlinkedCollapsed": true
              },
              "icon": "links-coming-in",
              "title": "骰出重围 的反向链接列表"
            }
          },
          {
            "id": "087b82b777f238b7",
            "type": "leaf",
            "state": {
              "type": "outgoing-link",
              "state": {
                "file": "自媒体内容/周报/2025-W02.md",
                "linksCollapsed": false,
                "unlinkedCollapsed": true
              },
              "icon": "links-going-out",
              "title": "2025-W02 的出链列表"
            }
          },
          {
            "id": "06f1d85e08133a89",
            "type": "leaf",
            "state": {
              "type": "tag",
              "state": {
                "sortOrder": "frequency",
                "useHierarchy": true
              },
              "icon": "lucide-tags",
              "title": "标签"
            }
          },
          {
            "id": "1e9c1dc0bfd5a808",
            "type": "leaf",
            "state": {
              "type": "outline",
              "state": {
                "file": "自媒体内容/周报/2025-W02.md"
              },
              "icon": "lucide-list",
              "title": "2025-W02 的大纲"
            }
          },
          {
            "id": "91fcd51908231f89",
            "type": "leaf",
            "state": {
              "type": "git-view",
              "state": {},
              "icon": "lucide-file",
              "title": "Plugin no longer active"
            }
          },
          {
            "id": "aa1333c27a3dbe22",
            "type": "leaf",
            "state": {
              "type": "calendar",
              "state": {},
              "icon": "lucide-file",
              "title": "Plugin no longer active"
            }
          }
        ],
        "currentTab": 5
      }
    ],
    "direction": "horizontal",
    "width": 200,
    "collapsed": true
  },
  "left-ribbon": {
    "hiddenItems": {
      "switcher:Open quick switcher": false,
      "graph:Open graph view": false,
      "canvas:Create new canvas": false,
      "daily-notes:Open today's daily note": false,
      "templates:Insert template": false,
      "command-palette:Open command palette": false,
      "markdown-importer:Open format converter": false,
      "zk-prefixer:Create new unique note": false,
      "obsidian-git:Open Git source control": false,
      "obsidian-excalidraw-plugin:Create new drawing": false,
      "table-editor-obsidian:Advanced Tables Toolbar": false
    }
  },
  "active": "bb98973169500b1a",
  "lastOpenFiles": [
    "游戏创意/完整/Dive Up/设计/关卡表.md",
    "游戏创意/完整/Mist Castle/剧本/实验记录.md",
    "游戏创意/完整/Mist Castle/剧本/剧本.md",
    "游戏创意/完整/Mist Castle/剧情/剧情.md",
    "游戏创意/完整/Mist Castle/剧本/奇迹的孤儿.md",
    "游戏创意/完整/Mist Castle/Mist Castle.md",
    "Clippings/不同游戏类型的市场生存空间以其他趋势——基于Steam评论数的分析 - 奶牛关.md",
    "Clippings/精华报告：如何科学预估一款Steam游戏的销量？_腾讯新闻.md",
    "Clippings/数据报告：Steam收入百万美元开发者只有1600个，他们有4个特点  游戏大观  GameLook.com.cn 1.md",
    "Clippings/Get Tangent At Distance Along Spline Affected by Length - Programming & Scripting  Blueprint - Epic Developer Community Forums.md",
    "Clippings/在虚幻引擎5.3和更高版本中使用现代化Xcode  虚幻引擎 5.5 文档  Epic Developer Community.md",
    "文字创作/癫火.md",
    "双喜.md",
    "文字创作/手.md",
    "文字创作/房间.md",
    "文字创作/2025217.md",
    "游戏创意/完整/调查深入/调查深入.md",
    "游戏创意/完整/调查深入",
    "游戏创意/草稿/房间.md",
    "游戏创意/草稿/猫别塔.md",
    "游戏创意/草稿/骰出重围.md",
    "游戏创意/草稿/像素狂潮.md",
    "游戏创意/草稿/棚户.md",
    "游戏创意/草稿/步履.md",
    "游戏创意/草稿/调查开始.md",
    "游戏创意/草稿/未命名.md",
    "游戏创意/活动/GGJ头脑风暴.md",
    "Archive/自媒体内容/视频选题",
    "Archive/自媒体内容/周报",
    "Archive/自媒体内容",
    "Archive/Pasted image 20250122122542.png",
    "Archive/Pasted Image 20250113114749_497.png",
    "Archive/Pasted Image 20250113114302_559.png",
    "游戏创意/完整/ATION/行动块/释放/连锁",
    "游戏创意/完整/ATION/行动块/释放/自主",
    "Pasted image 20250122122542.png",
    "游戏创意/完整/ATION/行动块/规则",
    "游戏创意/完整/ATION/行动块/属性/次生属性",
    "游戏创意/完整/ATION/行动块/属性/原生属性",
    "游戏创意/完整/ATION/卡牌/种类/未命名",
    "Pasted Image 20250113114749_497.png",
    "Pasted Image 20250113114302_559.png",
    "游戏创意/完整/Dive Up/设计/美术/VFX/Image/1月3日(5).png",
    "游戏创意/完整/Dive Up/设计/美术/VFX/Image/1月3日.gif",
    "游戏创意/完整/Dive Up/设计/美术/VFX/Image/1月3日(6).png",
    "游戏创意/完整/Dive Up/设计/美术/VFX/Image/1月3日(4).png",
    "未命名.canvas",
    "未命名 1.canvas"
  ]
}